git_quotes-0.1.1.data/data/hooks/prepare-commit-msg
git_quotes-0.1.1.data/data/hooks/quotes.json
quotes/__init__.py
quotes/git_quotes.py
quotes/groups.py
quotes/utils.py
quotes/hooks/prepare-commit-msg
quotes/hooks/quotes.json
git_quotes-0.1.1.dist-info/LICENSE
git_quotes-0.1.1.dist-info/METADATA
git_quotes-0.1.1.dist-info/WHEEL
git_quotes-0.1.1.dist-info/entry_points.txt
git_quotes-0.1.1.dist-info/top_level.txt
git_quotes-0.1.1.dist-info/RECORD
